hyoga/__init__.py
hyoga/demo.py
hyoga/core/__init__.py
hyoga/core/accessor.py
hyoga/core/config.py
hyoga/open/__init__.py
hyoga/open/aggregator.py
hyoga/open/downloader.py
hyoga/open/example.py
hyoga/open/local.py
hyoga/open/naturalearth.py
hyoga/open/paleoglaciers.py
hyoga/open/reprojected.py
hyoga/plot/__init__.py
hyoga/plot/colormaps.py
hyoga/plot/datasets.py
hyoga/plot/hillshade.py
hyoga/plot/scalebar.py
hyoga-0.3.2.dist-info/licenses/COPYING
hyoga-0.3.2.dist-info/METADATA
hyoga-0.3.2.dist-info/WHEEL
hyoga-0.3.2.dist-info/top_level.txt
hyoga-0.3.2.dist-info/RECORD
