Metadata-Version: 2.4
Name: hyoga
Version: 0.3.2
Summary: Paleoglacier modelling framework
Home-page: https://github.com/juseg/hyoga
Author: Julien Seguinot
Classifier: Development Status :: 3 - Alpha
Classifier: Intended Audience :: Science/Research
Classifier: License :: OSI Approved :: GNU General Public License v3 or later (GPLv3+)
Classifier: Programming Language :: Python :: 3
Classifier: Topic :: Scientific/Engineering
Requires-Python: >=3.9
License-File: COPYING
Requires-Dist: cf_xarray>=0.5.0
Requires-Dist: geopandas
Requires-Dist: matplotlib!=3.8.0,>=3.5
Requires-Dist: numpy
Requires-Dist: requests
Requires-Dist: rioxarray
Requires-Dist: scipy
Requires-Dist: xarray>=0.18
Provides-Extra: docs
Requires-Dist: contextily; extra == "docs"
Requires-Dist: netcdf4; extra == "docs"
Requires-Dist: pandas<2.2.0; extra == "docs"
Requires-Dist: sphinx; extra == "docs"
Requires-Dist: sphinx-autosummary-accessors; extra == "docs"
Requires-Dist: sphinx-book-theme>=0.3.3; extra == "docs"
Requires-Dist: sphinx-gallery; extra == "docs"
Provides-Extra: open
Requires-Dist: dask; extra == "open"
Dynamic: license-file
